component_scheduler/__init__.py
component_scheduler/scheduler.py
data_locality_system-0.0.5.dist-info/DESCRIPTION.rst
data_locality_system-0.0.5.dist-info/METADATA
data_locality_system-0.0.5.dist-info/RECORD
data_locality_system-0.0.5.dist-info/WHEEL
data_locality_system-0.0.5.dist-info/metadata.json
data_locality_system-0.0.5.dist-info/top_level.txt
dls/__init__.py
dls/dls_api.py
